list_all_files_recursively_short/README.MD
list_all_files_recursively_short/__init__.py
list_all_files_recursively_short/requirements.txt
list_all_files_recursively_short/thirdparty.json
list_all_files_recursively_short-0.10.dist-info/LICENSE.rst
list_all_files_recursively_short-0.10.dist-info/METADATA
list_all_files_recursively_short-0.10.dist-info/WHEEL
list_all_files_recursively_short-0.10.dist-info/top_level.txt
list_all_files_recursively_short-0.10.dist-info/RECORD
