Metadata-Version: 2.1
Name: list_all_files_recursively_short
Version: 0.10
Summary: List files + 8.3 path
Home-page: https://github.com/hansalemaos/list_all_files_recursively_short
Author: Johannes Fischer
Author-email: aulasparticularesdealemaosp@gmail.com
License: MIT
Keywords: 83,windows
Classifier: Development Status :: 4 - Beta
Classifier: Programming Language :: Python :: 3 :: Only
Classifier: Programming Language :: Python :: 3.10
Classifier: Topic :: Software Development :: Libraries :: Python Modules
Classifier: Topic :: Utilities
License-File: LICENSE.rst
